CODE_STRUCTURE.rst
MANIFEST.in
README.rst
requirements.txt
setup.cfg
setup.py
test_requirements.txt
mercator/__init__.py
mercator/errors.py
mercator/meta.py
mercator/version.py
mercator.egg-info/PKG-INFO
mercator.egg-info/SOURCES.txt
mercator.egg-info/dependency_links.txt
mercator.egg-info/not-zip-safe
mercator.egg-info/requires.txt
mercator.egg-info/top_level.txt