Metadata-Version: 2.1
Name: mercator
Version: 0.1.10
Summary: 0.1.10
Home-page: https://mercator.readthedocs.io/en/latest/
Author: NewStore Inc.
Author-email: engineering@newstore.com
License: UNKNOWN
Download-URL: https://github.com/NewStore/mercator/releases
Platform: UNKNOWN
Classifier: Development Status :: 5 - Production/Stable
Classifier: Environment :: Console
Classifier: License :: OSI Approved :: GNU General Public License v3 or later (GPLv3+)
Classifier: Operating System :: MacOS :: MacOS X
Classifier: Operating System :: POSIX
Classifier: Operating System :: POSIX :: Linux
Classifier: Programming Language :: Python
Classifier: Programming Language :: Python :: 3
Classifier: Programming Language :: Python :: 3.6
Classifier: Programming Language :: Python :: 3.7
Classifier: Programming Language :: Python :: Implementation
Classifier: Programming Language :: Python :: Implementation :: CPython
